wettingfront/__init__.py
wettingfront/__main__.py
wettingfront/models.py
wettingfront/py.typed
wettingfront/samples/example.jpg
wettingfront/samples/example.mp4
wettingfront-1.2.0.dist-info/LICENSE
wettingfront-1.2.0.dist-info/METADATA
wettingfront-1.2.0.dist-info/WHEEL
wettingfront-1.2.0.dist-info/entry_points.txt
wettingfront-1.2.0.dist-info/top_level.txt
wettingfront-1.2.0.dist-info/RECORD
