Metadata-Version: 2.1
Name: wettingfront
Version: 1.2.0
Summary: Wetting front analysis tool
Author-email: Jisoo Song <jeesoo9595@snu.ac.kr>
License: BSD 2-Clause License
Project-URL: homepage, https://github.com/JSS95/wettingfront
Project-URL: source, https://github.com/JSS95/wettingfront
Project-URL: documentation, https://wettingfront.readthedocs.io
Classifier: Development Status :: 5 - Production/Stable
Classifier: Intended Audience :: Science/Research
Classifier: License :: OSI Approved :: BSD License
Classifier: Programming Language :: Python
Classifier: Programming Language :: Python :: 3
Classifier: Programming Language :: Python :: 3.8
Classifier: Programming Language :: Python :: 3.9
Classifier: Programming Language :: Python :: 3.10
Classifier: Programming Language :: Python :: 3.11
Classifier: Programming Language :: Python :: 3.12
Classifier: Programming Language :: Python :: 3 :: Only
Classifier: Topic :: Scientific/Engineering
Classifier: Topic :: Scientific/Engineering :: Hydrology
Classifier: Topic :: Scientific/Engineering :: Physics
Classifier: Typing :: Typed
Classifier: Operating System :: Microsoft :: Windows
Classifier: Operating System :: POSIX
Classifier: Operating System :: Unix
Classifier: Operating System :: MacOS
Requires-Python: >=3.8
License-File: LICENSE
Requires-Dist: numpy
Requires-Dist: scipy
Requires-Dist: PyYAML
Requires-Dist: importlib-metadata ; python_version < "3.10"
Requires-Dist: importlib-resources ; python_version < "3.10"
Provides-Extra: dev
Requires-Dist: flake8 ; extra == 'dev'
Requires-Dist: flake8-docstrings ; extra == 'dev'
Requires-Dist: black ; extra == 'dev'
Requires-Dist: isort ; extra == 'dev'
Requires-Dist: docformatter ; extra == 'dev'
Requires-Dist: doc8 ; extra == 'dev'
Requires-Dist: mypy ; extra == 'dev'
Requires-Dist: types-PyYAML ; extra == 'dev'
Requires-Dist: wettingfront[doc,test] ; extra == 'dev'
Provides-Extra: doc
Requires-Dist: furo ; extra == 'doc'
Requires-Dist: sphinx ; extra == 'doc'
Requires-Dist: sphinx-autoapi ; extra == 'doc'
Requires-Dist: sphinx-tabs >=3.4.5 ; extra == 'doc'
Requires-Dist: matplotlib ; extra == 'doc'
Requires-Dist: pandas ; extra == 'doc'
Requires-Dist: wettingfront[img] ; extra == 'doc'
Provides-Extra: img
Requires-Dist: imageio ; extra == 'img'
Requires-Dist: av ; extra == 'img'
Provides-Extra: test
Requires-Dist: pytest ; extra == 'test'
Requires-Dist: wettingfront[img] ; extra == 'test'
